Metadata-Version: 2.1
Name: e-switch
Version: 1.0.0
Summary: hallo world this is my packaga for "e" tha packaga that switchas all "e"s with "a"s
Home-page: UNKNOWN
Author: Safyre Lyons
Author-email: lyons.safyre@gmail.com
License: MIT
Platform: UNKNOWN
